{
  "creds": {
    "noiseKey": {
      "private": {
        "type": "Buffer",
        "data": "0IV9gzpjF6yKq/lM43HPUIjLuAQhUyhs5SJLfcxRsHY="
      },
      "public": {
        "type": "Buffer",
        "data": "1fPmIsrWB347R3l08UOrqYtaUag1+MsWDrsKsIP9Gj8="
      }
    },
    "signedIdentityKey": {
      "private": {
        "type": "Buffer",
        "data": "GHL51eaadn4nCA1bxDtS3Y3Ev4b0G4sw7WX1+7f9VVc="
      },
      "public": {
        "type": "Buffer",
        "data": "laJdQ33b/NTAwbmsOqRlgE8zpYfGW5Jbkr3I6acftQ4="
      }
    },
    "signedPreKey": {
      "keyPair": {
        "private": {
          "type": "Buffer",
          "data": "YOUOy2iGGdooAiwlhMOuLW1ieJAHTQ25ySRWFNQPtGY="
        },
        "public": {
          "type": "Buffer",
          "data": "xOwXGKRHMfSy7npqkvIjJJpdLv2t/fLwonu988XV+gY="
        }
      },
      "signature": {
        "type": "Buffer",
        "data": "YzotQOKzbXn2mxKGUDX7Dg+nJxsXEZZSG5d9e3sUFpD45SlQ1l4htqHgwWqefU1Ryxaizb78QCTZw96n7FEnig=="
      },
      "keyId": 1
    },
    "registrationId": 116,
    "advSecretKey": "0QckIU7SyiTwSmU1kCJWqqFU4M9kNKR/CDeSmETywWc=",
    "processedHistoryMessages": [
      {
        "key": {
          "remoteJid": "6281349838609@s.whatsapp.net",
          "fromMe": true,
          "id": "5AFB0D9FBF13ED0A2BC10E019968FFF7"
        },
        "messageTimestamp": 1676378613
      },
      {
        "key": {
          "remoteJid": "6281349838609@s.whatsapp.net",
          "fromMe": true,
          "id": "7D7D6B370033925A50989F4B695AEF7D"
        },
        "messageTimestamp": 1676378614
      },
      {
        "key": {
          "remoteJid": "6281349838609@s.whatsapp.net",
          "fromMe": true,
          "id": "237D2B74ECC958DE041DAEF0CCA56722"
        },
        "messageTimestamp": 1676378620
      }
    ],
    "nextPreKeyId": 64,
    "firstUnuploadedPreKeyId": 64,
    "accountSettings": {
      "unarchiveChats": false
    },
    "account": {
      "details": "CNbpo/QGEPGDrp8GGAE=",
      "accountSignatureKey": "WKktuJ/VhJ0O6Sf1P0Xg0uQjWkGsIPCqCySt06I20gQ=",
      "accountSignature": "eW9dr2E8corpQ4nrbQLPMqRm1l//98vYmJjBwUfVuoAUBgdpNMljn7E+m/SShzoNGHz++hCM7IiCjCYjaT/dAQ==",
      "deviceSignature": "EkFtrD89X6loUwQEVKdQm/TkV3n+gamtWuU7qma+DyEfTLqkoUc6YGMhlm1AopZZLz6sUNDc/oDUtcrXKxVpiA=="
    },
    "me": {
      "id": "6281349838609:3@s.whatsapp.net",
      "name": "𝙕𝘼𝙇𝙇𝙭𝘽𝙊𝙏𝙕",
      "jid": "6281349838609@s.whatsapp.net"
    },
    "signalIdentities": [
      {
        "identifier": {
          "name": "6281349838609:3@s.whatsapp.net",
          "deviceId": 0
        },
        "identifierKey": {
          "type": "Buffer",
          "data": "BVipLbif1YSdDukn9T9F4NLkI1pBrCDwqgskrdOiNtIE"
        }
      }
    ],
    "platform": "android",
    "lastAccountSyncTimestamp": 1676378611,
    "myAppStateKeyId": "AAAAAPtY"
  },
  "keys": {
    "preKeys": {
      "1": {
        "private": {
          "type": "Buffer",
          "data": "wPnv04U2kVIjgRYe6+1OzGa4msqTdqLKRScVClQFj1g="
        },
        "public": {
          "type": "Buffer",
          "data": "74tUxUteWwst6iM7m7II7SlX+ZdRcL8dv4xjNm+ulls="
        }
      },
      "2": {
        "private": {
          "type": "Buffer",
          "data": "EC5W8EoHIqmJ5F+xp77XMbbSjQ601WJTZPqZcggKhHg="
        },
        "public": {
          "type": "Buffer",
          "data": "0lGglYKyE7l4EYyNxuh/HwoFxBXdOR9UoT+NDUaEeVA="
        }
      },
      "3": {
        "private": {
          "type": "Buffer",
          "data": "AMkDhj/l8kRZW0OjYUYKZVEpCfD/mqJ3eaKpN3F1SW8="
        },
        "public": {
          "type": "Buffer",
          "data": "Ea4pDxHvH22ga5iMO6khNbXk2uyVjVOSLYECKH8ifD4="
        }
      },
      "4": {
        "private": {
          "type": "Buffer",
          "data": "CK7+QJjFB4TMtdWuv8LdF5+bWvxEy0GnwkDmy3d3zXE="
        },
        "public": {
          "type": "Buffer",
          "data": "8+6OcJY8lBn12RwHX8AfZlbnlP67PjtftQCKKfGZ0Vk="
        }
      },
      "5": {
        "private": {
          "type": "Buffer",
          "data": "GNO0H/2GBX8P3fK1YZ/xWSJb5PYYA91FSkIA2NJgwFo="
        },
        "public": {
          "type": "Buffer",
          "data": "PDWK1PcBrMb0Rih+RsyZK8hph60lPuQToAWPg2gjXyM="
        }
      },
      "6": {
        "private": {
          "type": "Buffer",
          "data": "8PSGx+w3f8stvxnr12FOJGhZBGhLNuzIxcPrLJwzWGA="
        },
        "public": {
          "type": "Buffer",
          "data": "IMxFxlXc3hl+fpDv93+fjKGRzANFkdR8dc/Zna4oDVs="
        }
      },
      "7": {
        "private": {
          "type": "Buffer",
          "data": "EOdqA2knzKJhxcz7+GGhVsLagnLTZfxL0EwBMULhD2U="
        },
        "public": {
          "type": "Buffer",
          "data": "bSruvb8a7vRysS8qIWniVsnqDkPWF+m5aDdBUhS6vF8="
        }
      },
      "8": {
        "private": {
          "type": "Buffer",
          "data": "GJBKiz0D7kKWe/qJA5siNFHa213XBVbrWwVXpSND9nw="
        },
        "public": {
          "type": "Buffer",
          "data": "xY9TsTK80vJiA6oITsaXM063Smmsxbu04cg0V5V4AmE="
        }
      },
      "9": {
        "private": {
          "type": "Buffer",
          "data": "YFZz1ghWQ75LL2TdKFvaoq4n2YFPhM8fRLHc5y2BsHI="
        },
        "public": {
          "type": "Buffer",
          "data": "wKTzu7SXvgpOXXEJ+lfx2DN8WPvzZxT9TM1sarDVq24="
        }
      },
      "10": null,
      "11": {
        "private": {
          "type": "Buffer",
          "data": "AAcVnWL+A7icntqdKAbJS6MlYYxSNtu2P8c7pW60gVA="
        },
        "public": {
          "type": "Buffer",
          "data": "S/AJ6FH8PBsPGRd4375p4quci3Ftu6U1M4o9Texnkkg="
        }
      },
      "12": {
        "private": {
          "type": "Buffer",
          "data": "KPanU1uLDdR6F+i4Mp1kQRi8AywLpWwbfl/OBsxQeUM="
        },
        "public": {
          "type": "Buffer",
          "data": "cb474FIvxw9q3h6ZIGKmzNSC8xpigXd1GDRu2rxqsns="
        }
      },
      "13": {
        "private": {
          "type": "Buffer",
          "data": "kP3IhcihvE4meEeSHe51gScIcJJBSnPFwPLRYTiPrlI="
        },
        "public": {
          "type": "Buffer",
          "data": "2TtTnvjWezTJ5utbsnK9W4YXRyg+SXWfsuq4BkSTzRo="
        }
      },
      "14": null,
      "15": {
        "private": {
          "type": "Buffer",
          "data": "eNlnUJT/WVjsN9xwk0wSKz6+TW0mI2urMk2DS4+1424="
        },
        "public": {
          "type": "Buffer",
          "data": "eA32WMDmN+L3cBrLubthSb97pASgoz82XEmvOmcMIzA="
        }
      },
      "16": {
        "private": {
          "type": "Buffer",
          "data": "SFykPXyEV3IIjAxSNL1L1sGaNJMPMb3dT3gYzXUXyVs="
        },
        "public": {
          "type": "Buffer",
          "data": "uRy0oZ4qJLAVQmG+z4vbnROUpaO9HZCG9izNa0faIls="
        }
      },
      "17": {
        "private": {
          "type": "Buffer",
          "data": "QMMv+UNzNPQRbZRKJy8JYwKT091fLf6fFCq1OTRLDmg="
        },
        "public": {
          "type": "Buffer",
          "data": "O9omJL4F3PMbXYgALMWij2hCng7TPqENkJGH/iNBnCI="
        }
      },
      "18": null,
      "19": {
        "private": {
          "type": "Buffer",
          "data": "OC6QEiF3IeHP4lmZsawk5k0AaYs7QvRW390eradArlI="
        },
        "public": {
          "type": "Buffer",
          "data": "87hqwVuxvb/THUsBiKroG1CHzxLv6QtxLjzgyppl6mQ="
        }
      },
      "20": {
        "private": {
          "type": "Buffer",
          "data": "ACcWv5SKWpMK6Dqa/s9OrR+mOS5YqrEmSsFsYG+PUlg="
        },
        "public": {
          "type": "Buffer",
          "data": "V3wG+7LPKsi+ZLq2PuTY8WwG+K9ZdBahRuZncgCNahs="
        }
      },
      "21": {
        "private": {
          "type": "Buffer",
          "data": "iBN9tJJR30RQppBY5JeGIAjYdBBAuT/Wpco4QNTMc2I="
        },
        "public": {
          "type": "Buffer",
          "data": "h0Dr0Q7lRUXh7hBfFkESHW71aFbD2SuVDJTFyMER7H8="
        }
      },
      "22": {
        "private": {
          "type": "Buffer",
          "data": "IIsUUM4ooYIhLB0sDa4O+gdGPetDNygVbsCd4JxT7VQ="
        },
        "public": {
          "type": "Buffer",
          "data": "7AXOh/Pnndmbq3jsXnmPuAMT/1/aKEsEFefW1JOuWWQ="
        }
      },
      "23": null,
      "24": {
        "private": {
          "type": "Buffer",
          "data": "oBVICvmOdfGM80XbjFBhutZx6f8Q0TrD+GccABDgcl8="
        },
        "public": {
          "type": "Buffer",
          "data": "gnWTZ2p95e2pBT/noJ664ZfUEo7ssuI4Sgm5Fxb+eFU="
        }
      },
      "25": {
        "private": {
          "type": "Buffer",
          "data": "8Pgf6sSbi5TUFzP5m2TbNkn72pf8uPXuesV8CS0AEnE="
        },
        "public": {
          "type": "Buffer",
          "data": "RcJDGF75mX/cdgDHJGVDoQPWFEFvldYG+NF+oIfVpyA="
        }
      },
      "26": null,
      "27": {
        "private": {
          "type": "Buffer",
          "data": "KHXj0rDnjFwd+Dp9tcSibG1WT6iHTpBZYv6s/Jjmqm0="
        },
        "public": {
          "type": "Buffer",
          "data": "kpKJA8P05BzG7aHiLUvqro6S4M1kCGL98NEpWrVbWGQ="
        }
      },
      "28": {
        "private": {
          "type": "Buffer",
          "data": "6LhCzqBO9JIzYJe2vt97Yoa75HVrakbW98QH9zkZj14="
        },
        "public": {
          "type": "Buffer",
          "data": "WtxxtXP0kgpAE54HoMTdFkUJ7nq0Fye1nc56Y5XNfjY="
        }
      },
      "29": null,
      "30": {
        "private": {
          "type": "Buffer",
          "data": "IKbPpfhbAXlKWoi8ACc+X8J1mLHGykQs15lf2nHN8W8="
        },
        "public": {
          "type": "Buffer",
          "data": "BovDTRpZHn0Yc65TtIc8cfJGwU1ldnOnnZVjEiExE00="
        }
      },
      "32": {
        "private": {
          "type": "Buffer",
          "data": "kHzfEenRYGNxnWr3T42kvuo8M3gMxsx1HyinXQ4FWH0="
        },
        "public": {
          "type": "Buffer",
          "data": "e135ISTpQ37qw9DZcHPEj+Ym2cIhzFQtakNlT+f14Gg="
        }
      },
      "63": null
    },
    "sessions": {
      "6281349838609.0": {
        "_sessions": {
          "BZ8sl/rUicBSCC9VvzMtG978WVf8TR+tMzPN+zc2dgp+": {
            "registrationId": 673164180,
            "currentRatchet": {
              "ephemeralKeyPair": {
                "pubKey": "BbLF6ygitWtVh39C5Y0+T2o5dP3MUfe4G9NGP4MbLzMd",
                "privKey": "yGT4hybocnd0oRse3DF7kW01+vKMjoKajElKUvCRvXU="
              },
              "lastRemoteEphemeralKey": "BZeU4FGUfCJRkYa+GMICIYoVAyGYy16mUAPajLy/u/Fx",
              "previousCounter": -1,
              "rootKey": "A/PRqZ/LQ6SZd6T34LhKcVDyXH50wiIDCpUlvu7kLwI="
            },
            "indexInfo": {
              "baseKey": "BZ8sl/rUicBSCC9VvzMtG978WVf8TR+tMzPN+zc2dgp+",
              "baseKeyType": 2,
              "closed": -1,
              "used": 1676417983095,
              "created": 1676378613483,
              "remoteIdentityKey": "BVipLbif1YSdDukn9T9F4NLkI1pBrCDwqgskrdOiNtIE"
            },
            "_chains": {
              "BUPHT7J/cqa6eP/qaBzC18A3b0vrJYhmrB44nkgvJtcM": {
                "chainKey": {
                  "counter": 5
                },
                "chainType": 2,
                "messageKeys": {}
              },
              "BZeU4FGUfCJRkYa+GMICIYoVAyGYy16mUAPajLy/u/Fx": {
                "chainKey": {
                  "counter": 1,
                  "key": "oWix3cUGTfzDz0DnkWWGiYh9AjXXerzTSWi/+wFMkBc="
                },
                "chainType": 2,
                "messageKeys": {}
              },
              "BbLF6ygitWtVh39C5Y0+T2o5dP3MUfe4G9NGP4MbLzMd": {
                "chainKey": {
                  "counter": 33,
                  "key": "Fc0V3iw5Emal13UOWV77wgyuGc13gs7omlDZnIlbZs0="
                },
                "chainType": 1,
                "messageKeys": {}
              }
            }
          }
        },
        "version": "v1"
      },
      "6281392128956.0": {
        "_sessions": {
          "BVHJU6lkDVkS/bWHfgIj7fboFx60CyTS7a8/qj5NlukY": {
            "registrationId": 1779675758,
            "currentRatchet": {
              "ephemeralKeyPair": {
                "pubKey": "BbUbitlr+EHFHWYyMUZNkQu9M1Xhajdon+IpKrFdH3IE",
                "privKey": "eOjVCfeHn92xvRfCPUUVSzr/m/2urexE6sekGPtd5GA="
              },
              "lastRemoteEphemeralKey": "BR/wErQluwwOmfAPpmerq6ubDXPwJ04ZdbHdJ8oavq86",
              "previousCounter": 0,
              "rootKey": "j/eGjzvTyco4ekbmsQPs9z5FzJPM+98GI/cCdExNsTs="
            },
            "indexInfo": {
              "baseKey": "BVHJU6lkDVkS/bWHfgIj7fboFx60CyTS7a8/qj5NlukY",
              "baseKeyType": 2,
              "closed": -1,
              "used": 1676418252004,
              "created": 1676418252004,
              "remoteIdentityKey": "BSYXR0pNUvwv/cgG/pqSVyijlIbEfRzDK/eVpjBAcBVh"
            },
            "_chains": {
              "BR/wErQluwwOmfAPpmerq6ubDXPwJ04ZdbHdJ8oavq86": {
                "chainKey": {
                  "counter": 0,
                  "key": "wCPCb4300IUd+KFSxnI0ZNZKY54jcA4VCWZLVxf/0Kw="
                },
                "chainType": 2,
                "messageKeys": {}
              },
              "BbUbitlr+EHFHWYyMUZNkQu9M1Xhajdon+IpKrFdH3IE": {
                "chainKey": {
                  "counter": 7,
                  "key": "raW35m6wflhL7nT4VtjYtQQmcHBPtGnof3zbj1McGO0="
                },
                "chainType": 1,
                "messageKeys": {}
              }
            }
          }
        },
        "version": "v1"
      },
      "6287784028546:3.0": {
        "_sessions": {
          "BY+CPRao/N9HU3MfqeBskhSNJer7SkXLvcJImwc9vxEP": {
            "registrationId": 127,
            "currentRatchet": {
              "ephemeralKeyPair": {
                "pubKey": "Bc7GZlUbVxsz5Mo4FU9EtCj5mFoY3FSuK1a8jNhWk3cc",
                "privKey": "SLvxeR8Oad4XY6O2+KQMcEGaiYYRIcoerX7LyO2Ke2w="
              },
              "lastRemoteEphemeralKey": "BboGun581HwQa3wNJ6CHm/NeAt5olkoEMWPyyyaZCugC",
              "previousCounter": 0,
              "rootKey": "j39H9W2CIi3ChJQD13ayFLDI+pmG1dFDCZQlgm9IgNc="
            },
            "indexInfo": {
              "baseKey": "BY+CPRao/N9HU3MfqeBskhSNJer7SkXLvcJImwc9vxEP",
              "baseKeyType": 1,
              "closed": 1676418345476,
              "used": 1676418258292,
              "created": 1676418253865,
              "remoteIdentityKey": "BbNR36t1d3enoHASgu10aAw+7Dzi+IWwb0zsmvPWzcs/"
            },
            "_chains": {
              "BboGun581HwQa3wNJ6CHm/NeAt5olkoEMWPyyyaZCugC": {
                "chainKey": {
                  "counter": 0,
                  "key": "26AyQ2u4yMztJB86oD9xF5ngi3zioencTskRjCLpfPM="
                },
                "chainType": 2,
                "messageKeys": {}
              },
              "Bc7GZlUbVxsz5Mo4FU9EtCj5mFoY3FSuK1a8jNhWk3cc": {
                "chainKey": {
                  "counter": -1,
                  "key": "gkvISVw7q0W1MlGrN+h6W2lT89AonFKd+z4J+Epncxg="
                },
                "chainType": 1,
                "messageKeys": {}
              }
            }
          },
          "BdmiJQO6EuyJJp4opahQMo/BG2p1Wb5wxzPFKJGAx05+": {
            "registrationId": 127,
            "currentRatchet": {
              "ephemeralKeyPair": {
                "pubKey": "BVIky+uaI8O/7oNwZm5vyGH6uxDRZPEv3mkPuTZctZ8F",
                "privKey": "OKLJVrLByj1Ox97Lc038jzLWNHOwkxUwxOxQsz1xrUk="
              },
              "lastRemoteEphemeralKey": "BUCgbrHvt0j9dLWW6J9Jxrockhmck85pxpyj4bUfSTAR",
              "previousCounter": 0,
              "rootKey": "sw1EJgBZmdO24VkzewRg/rz+xEfeX4sPoVWqlfhEvuc="
            },
            "indexInfo": {
              "baseKey": "BdmiJQO6EuyJJp4opahQMo/BG2p1Wb5wxzPFKJGAx05+",
              "baseKeyType": 1,
              "closed": 1676418352615,
              "used": 1676418345474,
              "created": 1676418345474,
              "remoteIdentityKey": "BbNR36t1d3enoHASgu10aAw+7Dzi+IWwb0zsmvPWzcs/"
            },
            "_chains": {
              "BVIky+uaI8O/7oNwZm5vyGH6uxDRZPEv3mkPuTZctZ8F": {
                "chainKey": {
                  "counter": -1,
                  "key": "oAyLoVa0v0Zm9luzsHw+T7V6rYbyOESfsqgX+GE+jSs="
                },
                "chainType": 1,
                "messageKeys": {}
              }
            },
            "pendingPreKey": {
              "signedKeyId": 1,
              "baseKey": "BdmiJQO6EuyJJp4opahQMo/BG2p1Wb5wxzPFKJGAx05+",
              "preKeyId": 84
            }
          },
          "BUi0368WEGqoTsQ8IP05y/yn4YDu0vD07cwgHQ0PP5Yn": {
            "registrationId": 127,
            "currentRatchet": {
              "ephemeralKeyPair": {
                "pubKey": "BcamaNMfHRNk8QIrCT1gy2FPmqXxnOJJD1ORUpcPEG4J",
                "privKey": "WC4p3P9vAtyALMiXMkQbT8p90OPjTebs00pDK0vCCEw="
              },
              "lastRemoteEphemeralKey": "BRf/8ttIe2fW7/rrb4Betxy5ne+QWgZDcFktHlJBqSU6",
              "previousCounter": 0,
              "rootKey": "nQ9NJZ0b36eoq0PFMAGVQUtoJrA6S7eUswdPaI8Kn4E="
            },
            "indexInfo": {
              "baseKey": "BUi0368WEGqoTsQ8IP05y/yn4YDu0vD07cwgHQ0PP5Yn",
              "baseKeyType": 2,
              "closed": 1676457107411,
              "used": 1676418352619,
              "created": 1676418352619,
              "remoteIdentityKey": "BbNR36t1d3enoHASgu10aAw+7Dzi+IWwb0zsmvPWzcs/"
            },
            "_chains": {
              "BRf/8ttIe2fW7/rrb4Betxy5ne+QWgZDcFktHlJBqSU6": {
                "chainKey": {
                  "counter": 0,
                  "key": "q0CR1eBIVrTmqzcOBXt70VLsD3YHITVRlLmaqLGw1hc="
                },
                "chainType": 2,
                "messageKeys": {}
              },
              "BcamaNMfHRNk8QIrCT1gy2FPmqXxnOJJD1ORUpcPEG4J": {
                "chainKey": {
                  "counter": 0,
                  "key": "14ko8TPLJe4ARaFXwbyTi9BysnvvUHWB2a6OalAsDkM="
                },
                "chainType": 1,
                "messageKeys": {}
              }
            }
          },
          "BRaEm1uKxNZqP7sYgreMX8BL4IW8Eo6ve3HkWCSztpdL": {
            "registrationId": 127,
            "currentRatchet": {
              "ephemeralKeyPair": {
                "pubKey": "BYa35U+2TT9kWvVV+GcSW3d1Al6PeWKBQ6a6buiqJwJg",
                "privKey": "AI/45YghWutOihwWCjrh4fzMFoI1USCPNFO7dcJolnM="
              },
              "lastRemoteEphemeralKey": "Bbn/+mEae3ydjqHeLdd2hr8SaXZX5zfarIBIbenoAFkt",
              "previousCounter": 0,
              "rootKey": "P9EXx1OHE0sqhT2nzSypnW/jePyCGVe+Z2uvQwW7nQ0="
            },
            "indexInfo": {
              "baseKey": "BRaEm1uKxNZqP7sYgreMX8BL4IW8Eo6ve3HkWCSztpdL",
              "baseKeyType": 2,
              "closed": 1676457110024,
              "used": 1676457107422,
              "created": 1676457107422,
              "remoteIdentityKey": "BbNR36t1d3enoHASgu10aAw+7Dzi+IWwb0zsmvPWzcs/"
            },
            "_chains": {
              "Bbn/+mEae3ydjqHeLdd2hr8SaXZX5zfarIBIbenoAFkt": {
                "chainKey": {
                  "counter": 0,
                  "key": "e3G1C3wGVii2cz3FOnpHFHn9RYOLOjPNW7YUMBC4HCc="
                },
                "chainType": 2,
                "messageKeys": {}
              },
              "BYa35U+2TT9kWvVV+GcSW3d1Al6PeWKBQ6a6buiqJwJg": {
                "chainKey": {
                  "counter": -1,
                  "key": "jP7JflBvPNVCrK2SQMhgxDXfUXxLCK+htSgrwsdZIcI="
                },
                "chainType": 1,
                "messageKeys": {}
              }
            }
          },
          "BeGJrQQ/+0rnRHzrRbVicr8OQxCCUlicpLK1b+GgL788": {
            "registrationId": 127,
            "currentRatchet": {
              "ephemeralKeyPair": {
                "pubKey": "BYWkyaO2Jr2uYtyF7V/O0/AgF3MefvOk4Nz31XPniM46",
                "privKey": "4E++C5+23FAaqGRt+V72pue0YCMNFQQMPaDEJE/133M="
              },
              "lastRemoteEphemeralKey": "BUCgbrHvt0j9dLWW6J9Jxrockhmck85pxpyj4bUfSTAR",
              "previousCounter": 0,
              "rootKey": "xBpB8Hm/HKb23Sys49D0thViOb24jfbJLNZSFUK09Ng="
            },
            "indexInfo": {
              "baseKey": "BeGJrQQ/+0rnRHzrRbVicr8OQxCCUlicpLK1b+GgL788",
              "baseKeyType": 1,
              "closed": 1676503120519,
              "used": 1676457110016,
              "created": 1676457110016,
              "remoteIdentityKey": "BbNR36t1d3enoHASgu10aAw+7Dzi+IWwb0zsmvPWzcs/"
            },
            "_chains": {
              "BYWkyaO2Jr2uYtyF7V/O0/AgF3MefvOk4Nz31XPniM46": {
                "chainKey": {
                  "counter": 0,
                  "key": "7ZtCFI9iF6UoEJMnPVAPU1dwlllDbeHHdEH80G6mXz4="
                },
                "chainType": 1,
                "messageKeys": {}
              }
            },
            "pendingPreKey": {
              "signedKeyId": 1,
              "baseKey": "BeGJrQQ/+0rnRHzrRbVicr8OQxCCUlicpLK1b+GgL788",
              "preKeyId": 77
            }
          },
          "BcSZ/19XszfRPPuIhVF+f+UBRYaPYqV+CWAs7Zo6dXQ9": {
            "registrationId": 127,
            "currentRatchet": {
              "ephemeralKeyPair": {
                "pubKey": "BXim0ZOnk1E13//pFkFFUt9XOX/ljjJp1ZG5GjfPJtN0",
                "privKey": "YOn0k4PaRII9Wck3VCApyfsinXYL3iGJMcTlhDXUJX8="
              },
              "lastRemoteEphemeralKey": "BUCgbrHvt0j9dLWW6J9Jxrockhmck85pxpyj4bUfSTAR",
              "previousCounter": 0,
              "rootKey": "L9A4ODwFlAco5lnUaHHglYvqfZa1RhxCyC0VqsCe9Sc="
            },
            "indexInfo": {
              "baseKey": "BcSZ/19XszfRPPuIhVF+f+UBRYaPYqV+CWAs7Zo6dXQ9",
              "baseKeyType": 1,
              "closed": 1676518891524,
              "used": 1676503120517,
              "created": 1676503120517,
              "remoteIdentityKey": "BbNR36t1d3enoHASgu10aAw+7Dzi+IWwb0zsmvPWzcs/"
            },
            "_chains": {
              "BXim0ZOnk1E13//pFkFFUt9XOX/ljjJp1ZG5GjfPJtN0": {
                "chainKey": {
                  "counter": 0,
                  "key": "Bf+qt0NaH085f0IbyIAqoXECzWsT7xzF0XBWDylApTE="
                },
                "chainType": 1,
                "messageKeys": {}
              }
            },
            "pendingPreKey": {
              "signedKeyId": 1,
              "baseKey": "BcSZ/19XszfRPPuIhVF+f+UBRYaPYqV+CWAs7Zo6dXQ9",
              "preKeyId": 78
            }
          },
          "BdStGMGdZ32MVwck7DK9perc2z8eEn/habqaf3KO5iMP": {
            "registrationId": 127,
            "currentRatchet": {
              "ephemeralKeyPair": {
                "pubKey": "BS9IoVZbaw8yKgPfnqD5izYOpVMvypbST7zMt7lnmkk1",
                "privKey": "wEAcknsNJ8/oZVKnwUWkvbLtaWU+jmBbqKa4GVA3lks="
              },
              "lastRemoteEphemeralKey": "BXaIYkpU//GFPesPPK5VgyEvgR8tnHcA8w2oTXbw3FkB",
              "previousCounter": 0,
              "rootKey": "EZnRXCl27lHUvUMHZ0Xb0pmtc3nAO+twJTimw18BNek="
            },
            "indexInfo": {
              "baseKey": "BdStGMGdZ32MVwck7DK9perc2z8eEn/habqaf3KO5iMP",
              "baseKeyType": 1,
              "closed": -1,
              "used": 1676590390983,
              "created": 1676518891522,
              "remoteIdentityKey": "BbNR36t1d3enoHASgu10aAw+7Dzi+IWwb0zsmvPWzcs/"
            },
            "_chains": {
              "BVvSHu8NqLyBOcdc5e7vD2wbhQpj5mD6NPdPf1Fc9sta": {
                "chainKey": {
                  "counter": 1
                },
                "chainType": 2,
                "messageKeys": {}
              },
              "BdLyy9ce6FzsRbhLb10up1nlPGlrdTlFmgk37zpG3TAz": {
                "chainKey": {
                  "counter": 0
                },
                "chainType": 2,
                "messageKeys": {}
              },
              "BXaIYkpU//GFPesPPK5VgyEvgR8tnHcA8w2oTXbw3FkB": {
                "chainKey": {
                  "counter": 0,
                  "key": "huTThJ30juZyf9RR0NFTA+aAJd7ZnI+fCqmZCsoU5Es="
                },
                "chainType": 2,
                "messageKeys": {}
              },
              "BS9IoVZbaw8yKgPfnqD5izYOpVMvypbST7zMt7lnmkk1": {
                "chainKey": {
                  "counter": 0,
                  "key": "ocich9OQE3p4+u3yPeQ4F47UyyoQYXY9zu2I1LSyDlk="
                },
                "chainType": 1,
                "messageKeys": {}
              }
            }
          }
        },
        "version": "v1"
      },
      "6281327238906:24.0": {
        "_sessions": {
          "BTSTHkctkve6jGjolYxqpZTbfXd9g7uEwkXBLJ6qES46": {
            "registrationId": 232,
            "currentRatchet": {
              "ephemeralKeyPair": {
                "pubKey": "BcGvIJTTOG3hkvOZI4hhN1XBTst9HoiEsHj8ope6/Fdc",
                "privKey": "8P/d+U3JbSn2Uccg2EkwMVSITfh4opj90UyQdZRlK0Q="
              },
              "lastRemoteEphemeralKey": "BaE4/M4U4xokbrB803u+2MgBJ0F/T+1TrAF5i5Jh+nE/",
              "previousCounter": 0,
              "rootKey": "VmVMQcJQ/sJb44QNFCFyTTZ4BmyXZFR8NalR/bqAssc="
            },
            "indexInfo": {
              "baseKey": "BTSTHkctkve6jGjolYxqpZTbfXd9g7uEwkXBLJ6qES46",
              "baseKeyType": 1,
              "closed": 1676418259360,
              "used": 1676418253871,
              "created": 1676418253871,
              "remoteIdentityKey": "BaeoKsTnCKeS4ev9M8FjYWE6JmNBEjQ8XFC4zEzomolu"
            },
            "_chains": {
              "BcGvIJTTOG3hkvOZI4hhN1XBTst9HoiEsHj8ope6/Fdc": {
                "chainKey": {
                  "counter": 0,
                  "key": "WXMBzTMEv2mCBboFoT2BBsVm8BcIVzw/jEHZZKL6vc4="
                },
                "chainType": 1,
                "messageKeys": {}
              }
            },
            "pendingPreKey": {
              "signedKeyId": 1,
              "baseKey": "BTSTHkctkve6jGjolYxqpZTbfXd9g7uEwkXBLJ6qES46",
              "preKeyId": 49
            }
          },
          "BcFUVDj4FBTVmRnTRKIItomz7KUVkRyP3n0BDMA91bpM": {
            "registrationId": 232,
            "currentRatchet": {
              "ephemeralKeyPair": {
                "pubKey": "BeNpN2doKQv51uPhYnGsxfpJAnzCxmPXPZ7V/CRDkC4p",
                "privKey": "oJ75YbNHouYWPn/mwhETchgLIiIAupNEpiDuPrA6+nM="
              },
              "lastRemoteEphemeralKey": "BTx7feUiqtEDIryLtHVU0+59SAQFn8NJaKNJd7Mk3AVb",
              "previousCounter": 0,
              "rootKey": "lm1xFyODmMZqOrweHWYvK3bpEGvrrYftFCaaFrDe0sk="
            },
            "indexInfo": {
              "baseKey": "BcFUVDj4FBTVmRnTRKIItomz7KUVkRyP3n0BDMA91bpM",
              "baseKeyType": 2,
              "closed": 1676418345567,
              "used": 1676418259366,
              "created": 1676418259366,
              "remoteIdentityKey": "BaeoKsTnCKeS4ev9M8FjYWE6JmNBEjQ8XFC4zEzomolu"
            },
            "_chains": {
              "BTx7feUiqtEDIryLtHVU0+59SAQFn8NJaKNJd7Mk3AVb": {
                "chainKey": {
                  "counter": 0,
                  "key": "rZD7LcL1ymdYlHVMiKfRXRgUa3/jC6jdE+wCmop9tAQ="
                },
                "chainType": 2,
                "messageKeys": {}
              },
              "BeNpN2doKQv51uPhYnGsxfpJAnzCxmPXPZ7V/CRDkC4p": {
                "chainKey": {
                  "counter": -1,
                  "key": "CJl2xF6wX4ypOg7T5IfDLhMD46vV0iDkru6ifeh6oHc="
                },
                "chainType": 1,
                "messageKeys": {}
              }
            }
          },
          "Bc8a23yQY2EJJt0gt8bkbn6i2qpgcE+FGegt5woh0RFT": {
            "registrationId": 232,
            "currentRatchet": {
              "ephemeralKeyPair": {
                "pubKey": "BZkrt32c2CvMIwmmYiaJAlOfh0qmdeZNFuYBLEaHxgYx",
                "privKey": "sBUeeNbUrDBDuJOaaGupOguzlJnJm8qRw+JA95K6CU0="
              },
              "lastRemoteEphemeralKey": "BcqY3EE0CQ50Jh5FJtWCcBzJ4r0AT0Nz+zCRks2PCnZf",
              "previousCounter": 0,
              "rootKey": "erBTN+NREmWbiNXY9l1gXLPMXFH8qJ+ZbWUb7BFYmkk="
            },
            "indexInfo": {
              "baseKey": "Bc8a23yQY2EJJt0gt8bkbn6i2qpgcE+FGegt5woh0RFT",
              "baseKeyType": 1,
              "closed": 1676457110148,
              "used": 1676418356753,
              "created": 1676418345566,
              "remoteIdentityKey": "BaeoKsTnCKeS4ev9M8FjYWE6JmNBEjQ8XFC4zEzomolu"
            },
            "_chains": {
              "BcqY3EE0CQ50Jh5FJtWCcBzJ4r0AT0Nz+zCRks2PCnZf": {
                "chainKey": {
                  "counter": 0,
                  "key": "6D+AD6mz7eFg+36Xe1TDVx5Uo6sSGvEoZx+DFuQsgBs="
                },
                "chainType": 2,
                "messageKeys": {}
              },
              "BZkrt32c2CvMIwmmYiaJAlOfh0qmdeZNFuYBLEaHxgYx": {
                "chainKey": {
                  "counter": -1,
                  "key": "ZfwdnYuxKYM8zCOd9tC1vKlrvM4k6rcwjXCpPv2J/hw="
                },
                "chainType": 1,
                "messageKeys": {}
              }
            }
          },
          "BYeHXMilYY0ECxIPX3u+d08PqWgX46WqT4IDGgUwF7Zx": {
            "registrationId": 232,
            "currentRatchet": {
              "ephemeralKeyPair": {
                "pubKey": "BeG2PhuvVdQJA8ygtlbxLSt/7ss1CHf9AEhC5A8BQ98Z",
                "privKey": "KK1rlEmDNvQRMAiV+C49kuzAPFEQnDYoRK/iJt3neGE="
              },
              "lastRemoteEphemeralKey": "BaE4/M4U4xokbrB803u+2MgBJ0F/T+1TrAF5i5Jh+nE/",
              "previousCounter": 0,
              "rootKey": "f9quoPad0vpPbJOSphWkZgy2hZzkViA3n28gqlYhkOs="
            },
            "indexInfo": {
              "baseKey": "BYeHXMilYY0ECxIPX3u+d08PqWgX46WqT4IDGgUwF7Zx",
              "baseKeyType": 1,
              "closed": 1676518891119,
              "used": 1676457110145,
              "created": 1676457110145,
              "remoteIdentityKey": "BaeoKsTnCKeS4ev9M8FjYWE6JmNBEjQ8XFC4zEzomolu"
            },
            "_chains": {
              "BeG2PhuvVdQJA8ygtlbxLSt/7ss1CHf9AEhC5A8BQ98Z": {
                "chainKey": {
                  "counter": 1,
                  "key": "Hb/zM+jn6Xzu2fmDseb+BKhYmYPgvRFpLLyoqiZjQUU="
                },
                "chainType": 1,
                "messageKeys": {}
              }
            },
            "pendingPreKey": {
              "signedKeyId": 1,
              "baseKey": "BYeHXMilYY0ECxIPX3u+d08PqWgX46WqT4IDGgUwF7Zx",
              "preKeyId": 52
            }
          },
          "BZkld42r8cZbYiabR+D61u9i8DtjSAb3/90bwO/VzUNU": {
            "registrationId": 232,
            "currentRatchet": {
              "ephemeralKeyPair": {
                "pubKey": "BXKGiGxwI1dvVz2uC6Xi4d93OqR4XgSXilaKneiUF2ZW",
                "privKey": "8Cfk7C421MqrC+DKkxeMDz8DoaJU4BTOi74Mkpg/sn8="
              },
              "lastRemoteEphemeralKey": "BbePCDlf7eYKP/6gJrM/IZgTC8ug6sHzZ28VfjHrWVJs",
              "previousCounter": 0,
              "rootKey": "VRjbX+QlSGKK7Mzp56yELAR4JmU2gwn2ulztPdfOhIM="
            },
            "indexInfo": {
              "baseKey": "BZkld42r8cZbYiabR+D61u9i8DtjSAb3/90bwO/VzUNU",
              "baseKeyType": 1,
              "closed": 1676564717613,
              "used": 1676526585644,
              "created": 1676518891117,
              "remoteIdentityKey": "BaeoKsTnCKeS4ev9M8FjYWE6JmNBEjQ8XFC4zEzomolu"
            },
            "_chains": {
              "BbePCDlf7eYKP/6gJrM/IZgTC8ug6sHzZ28VfjHrWVJs": {
                "chainKey": {
                  "counter": 0,
                  "key": "/seDs4Jilq5eEYyX+LSoMlTNQduT3LArGdFolwPeFck="
                },
                "chainType": 2,
                "messageKeys": {}
              },
              "BXKGiGxwI1dvVz2uC6Xi4d93OqR4XgSXilaKneiUF2ZW": {
                "chainKey": {
                  "counter": -1,
                  "key": "V2SsQ2PTSJG4wGgU1DQ7UIchVcjtFwQy1LWP8dwUnf0="
                },
                "chainType": 1,
                "messageKeys": {}
              }
            }
          },
          "BUNTzEW21/sqOn01rW79mcJHwVzenPatipVGHel/jgo7": {
            "registrationId": 232,
            "currentRatchet": {
              "ephemeralKeyPair": {
                "pubKey": "BaEot7347TEkjws6osW6RxqZJFMFGY9YE1w2p5ozJCZt",
                "privKey": "8AQNHCrI8Q1kxDFFkdNf+n5Cb4mP8HjHJ7i/UHoMU3E="
              },
              "lastRemoteEphemeralKey": "BaE4/M4U4xokbrB803u+2MgBJ0F/T+1TrAF5i5Jh+nE/",
              "previousCounter": 0,
              "rootKey": "ywspAveHHK2+AzFI1i44791ahjLgezt5iehkkkjRWEg="
            },
            "indexInfo": {
              "baseKey": "BUNTzEW21/sqOn01rW79mcJHwVzenPatipVGHel/jgo7",
              "baseKeyType": 1,
              "closed": 1676565832127,
              "used": 1676564717604,
              "created": 1676564717604,
              "remoteIdentityKey": "BaeoKsTnCKeS4ev9M8FjYWE6JmNBEjQ8XFC4zEzomolu"
            },
            "_chains": {
              "BaEot7347TEkjws6osW6RxqZJFMFGY9YE1w2p5ozJCZt": {
                "chainKey": {
                  "counter": 0,
                  "key": "fjvU+pfrDpPic0u6hk0XvKTLAl3YsS1YUwN7OdFuPO4="
                },
                "chainType": 1,
                "messageKeys": {}
              }
            },
            "pendingPreKey": {
              "signedKeyId": 1,
              "baseKey": "BUNTzEW21/sqOn01rW79mcJHwVzenPatipVGHel/jgo7",
              "preKeyId": 108
            }
          },
          "BedgCwlKgdZbHgtoQV+ZDqJSAlhsjYbj7xF8nhiYgKdu": {
            "registrationId": 232,
            "currentRatchet": {
              "ephemeralKeyPair": {
                "pubKey": "BVL3p7d4ibuqTO7QhDXCoX3B7FZWtxo3xPCRWwppxXdQ",
                "privKey": "WDaRHlHF0d2YZANpIZR23pzfoFcwQKFb90VDfUzhIE0="
              },
              "lastRemoteEphemeralKey": "BbckHQl00ayV7Vd6i47W8RvpXVagC+K9z9UrcR9MxYcJ",
              "previousCounter": 0,
              "rootKey": "LTye8FG6vHqP2eoh31zjFeEqsTclkIM2xaIqL2ydBEU="
            },
            "indexInfo": {
              "baseKey": "BedgCwlKgdZbHgtoQV+ZDqJSAlhsjYbj7xF8nhiYgKdu",
              "baseKeyType": 1,
              "closed": -1,
              "used": 1676590391248,
              "created": 1676565832125,
              "remoteIdentityKey": "BaeoKsTnCKeS4ev9M8FjYWE6JmNBEjQ8XFC4zEzomolu"
            },
            "_chains": {
              "BbckHQl00ayV7Vd6i47W8RvpXVagC+K9z9UrcR9MxYcJ": {
                "chainKey": {
                  "counter": 1,
                  "key": "wBTNZ20gO2BzQON/3A258akBKmQ9wzKI1ppV9nwbbbc="
                },
                "chainType": 2,
                "messageKeys": {}
              },
              "BVL3p7d4ibuqTO7QhDXCoX3B7FZWtxo3xPCRWwppxXdQ": {
                "chainKey": {
                  "counter": 0,
                  "key": "mLStS8tggcQrQ1IfEM6lAYD2zbWZZEo3sbRz0ENGHcI="
                },
                "chainType": 1,
                "messageKeys": {}
              }
            }
          }
        },
        "version": "v1"
      },
      "6281327238906.0": {
        "_sessions": {
          "BTWPm06XPLf6xWvtBnzEosnQrlCD/tedZw3w7dDa9ZkL": {
            "registrationId": 866430343,
            "currentRatchet": {
              "ephemeralKeyPair": {
                "pubKey": "BTui7ye2hW5Zkr3HujYwG1tJcwZ7FV7Xh9aahe65vtda",
                "privKey": "gG3kGmBL7HIqYZazG9/j6fCJ4CJC3MMre8Vay+00XXI="
              },
              "lastRemoteEphemeralKey": "BdmMnX1c9x/+sBk5ZsHber45zzNJ1240LwfagRVZhckx",
              "previousCounter": 0,
              "rootKey": "+1Eibb876j5+6D2/czH8nm3agjt8ujDxnN69+Tlqv78="
            },
            "indexInfo": {
              "baseKey": "BTWPm06XPLf6xWvtBnzEosnQrlCD/tedZw3w7dDa9ZkL",
              "baseKeyType": 1,
              "closed": -1,
              "used": 1676418253876,
              "created": 1676418253876,
              "remoteIdentityKey": "BbE9lyzzdedrzAV/LKIvHMzc1cnoQkcpcPNGVD+Yo3ha"
            },
            "_chains": {
              "BTui7ye2hW5Zkr3HujYwG1tJcwZ7FV7Xh9aahe65vtda": {
                "chainKey": {
                  "counter": 7,
                  "key": "dx/G3OuoDfyc4mFWzk8TKPDvAPyzia8WSWsIbtnC8Nk="
                },
                "chainType": 1,
                "messageKeys": {}
              }
            },
            "pendingPreKey": {
              "signedKeyId": 1,
              "baseKey": "BTWPm06XPLf6xWvtBnzEosnQrlCD/tedZw3w7dDa9ZkL",
              "preKeyId": 6248977
            }
          }
        },
        "version": "v1"
      },
      "6281333154367.0": {
        "_sessions": {
          "BbtQUppKnmIwKHkt54vc5ivmh2vQXL+MWDdNotMqTahR": {
            "registrationId": 1701057898,
            "currentRatchet": {
              "ephemeralKeyPair": {
                "pubKey": "Bb4BjZSWXLNT0KXU41hHU7D+gwwJULpjY+AcvpdbMDpL",
                "privKey": "qHGPRnPdALQpZAB05dQwQsJtTzCs1oRpy3LuywtBs2c="
              },
              "lastRemoteEphemeralKey": "BSkSq0dl1gfxCUDhIbyZ/gHmnYQkYQmZHmrIgH1czjxO",
              "previousCounter": 2,
              "rootKey": "zm9JCuR7TXNEdudN0To8tIJKk5/UY+cqvwrh8b1rdaE="
            },
            "indexInfo": {
              "baseKey": "BbtQUppKnmIwKHkt54vc5ivmh2vQXL+MWDdNotMqTahR",
              "baseKeyType": 1,
              "closed": 1676426750811,
              "used": 1676458569670,
              "created": 1676418253881,
              "remoteIdentityKey": "BZ3hAt1Kskouw5Zp//nyNDVOPjWQ9xgCBZVkKzpVoI9k"
            },
            "_chains": {
              "BU1JnDtbVcJGWOe+1UT3MsLw1DmyNgO/flMbyTzTe/Iu": {
                "chainKey": {
                  "counter": 1
                },
                "chainType": 2,
                "messageKeys": {}
              },
              "BXmbrZtmxas2rhHkT/KjUdc20UNzmOE7Dqg9sPtnHtEa": {
                "chainKey": {
                  "counter": 0
                },
                "chainType": 2,
                "messageKeys": {}
              },
              "BVb0VhYql/ILm0la09AUdWxWG+NCro6SbOEx7Tz3RsYS": {
                "chainKey": {
                  "counter": 0
                },
                "chainType": 2,
                "messageKeys": {}
              },
              "BdTgavOUcwEpqFFjDQ6zMPPmQc6meif8xrGbnB+IwsNH": {
                "chainKey": {
                  "counter": 0
                },
                "chainType": 2,
                "messageKeys": {}
              },
              "BT9Y7pll4yhwFwuy3lMgdDaWQvp5ov7vSkUtDEPDWMBW": {
                "chainKey": {
                  "counter": 0
                },
                "chainType": 2,
                "messageKeys": {}
              },
              "BXzfb7cFSXqhWxDJAz+Z6JgnJ+ALbwQqNV+4mglBP4ox": {
                "chainKey": {
                  "counter": 1
                },
                "chainType": 2,
                "messageKeys": {}
              },
              "BSkSq0dl1gfxCUDhIbyZ/gHmnYQkYQmZHmrIgH1czjxO": {
                "chainKey": {
                  "counter": 0,
                  "key": "maW0Z1VcU7Ep6Isg4mwPShVEqQutY7c4+d5H6myH/QU="
                },
                "chainType": 2,
                "messageKeys": {}
              },
              "Bb4BjZSWXLNT0KXU41hHU7D+gwwJULpjY+AcvpdbMDpL": {
                "chainKey": {
                  "counter": -1,
                  "key": "9YzENQ78Wei8q+VZy7F2Ope7rH9FkcW0V4jkrlbZIDI="
                },
                "chainType": 1,
                "messageKeys": {}
              }
            }
          },
          "BYFLQWVi154GkadIkhc8ywm1GvBde73/ld2HlmL3LCZS": {
            "registrationId": 1701057898,
            "currentRatchet": {
              "ephemeralKeyPair": {
                "pubKey": "BY3MDuTJWx2CQ8wjWuLFppirp5l6i2va02MpnuXYRGxZ",
                "privKey": "qOl8JUqCnyrO66iPD5ddr+SFORbrZHr/AtaG1sBRKkU="
              },
              "lastRemoteEphemeralKey": "BSkSq0dl1gfxCUDhIbyZ/gHmnYQkYQmZHmrIgH1czjxO",
              "previousCounter": -1,
              "rootKey": "wQ9PV/LgsZDaAsSK7d3NPWOmne4GZfuiTfmf/0av4jc="
            },
            "indexInfo": {
              "baseKey": "BYFLQWVi154GkadIkhc8ywm1GvBde73/ld2HlmL3LCZS",
              "baseKeyType": 1,
              "closed": 1676426751277,
              "used": 1676426750802,
              "created": 1676426750802,
              "remoteIdentityKey": "BZ3hAt1Kskouw5Zp//nyNDVOPjWQ9xgCBZVkKzpVoI9k"
            },
            "_chains": {
              "BSkSq0dl1gfxCUDhIbyZ/gHmnYQkYQmZHmrIgH1czjxO": {
                "chainKey": {
                  "counter": 0,
                  "key": "jWOaa9alXTczbn4HVoghuZpJquv0ellJApY75ms2rqc="
                },
                "chainType": 2,
                "messageKeys": {}
              },
              "BY3MDuTJWx2CQ8wjWuLFppirp5l6i2va02MpnuXYRGxZ": {
                "chainKey": {
                  "counter": -1,
                  "key": "Y/0A9A/3b7Ipgtu80cDewmbTJH9KVDDPMGgKSZyz5NU="
                },
                "chainType": 1,
                "messageKeys": {}
              }
            },
            "pendingPreKey": {
              "signedKeyId": 0,
              "baseKey": "BYFLQWVi154GkadIkhc8ywm1GvBde73/ld2HlmL3LCZS",
              "preKeyId": 11263142
            }
          },
          "BUqNseoyE2Xffv+ALzGDs3zfZgKSeCTl2E+yYccs4mtX": {
            "registrationId": 1701057898,
            "currentRatchet": {
              "ephemeralKeyPair": {
                "pubKey": "Bcdt0bYSZxBLFe2IQe8KMlgm/Ggs7xWLHhT4aundWRAY",
                "privKey": "CNTv8dxKj6KQeWg8aNpSfoU7ck0xnhewZzja8UiE/Ws="
              },
              "lastRemoteEphemeralKey": "BSkSq0dl1gfxCUDhIbyZ/gHmnYQkYQmZHmrIgH1czjxO",
              "previousCounter": -1,
              "rootKey": "LVLBPTblg7mKafBfTYWB8HkNRWkKd8TnNgZfMyWOrR4="
            },
            "indexInfo": {
              "baseKey": "BUqNseoyE2Xffv+ALzGDs3zfZgKSeCTl2E+yYccs4mtX",
              "baseKeyType": 1,
              "closed": 1676458652961,
              "used": 1676426751263,
              "created": 1676426751263,
              "remoteIdentityKey": "BZ3hAt1Kskouw5Zp//nyNDVOPjWQ9xgCBZVkKzpVoI9k"
            },
            "_chains": {
              "BSkSq0dl1gfxCUDhIbyZ/gHmnYQkYQmZHmrIgH1czjxO": {
                "chainKey": {
                  "counter": 0,
                  "key": "ZNlQXEOZMUPCADvMwzq7OBrVd9riwea1F65qq1Q+VAU="
                },
                "chainType": 2,
                "messageKeys": {}
              },
              "Bcdt0bYSZxBLFe2IQe8KMlgm/Ggs7xWLHhT4aundWRAY": {
                "chainKey": {
                  "counter": 0,
                  "key": "Z/oL+JflVb4y0gpKZ7qzPWozxcPWmQSVg7U2e39EJdE="
                },
                "chainType": 1,
                "messageKeys": {}
              }
            },
            "pendingPreKey": {
              "signedKeyId": 0,
              "baseKey": "BUqNseoyE2Xffv+ALzGDs3zfZgKSeCTl2E+yYccs4mtX",
              "preKeyId": 11262641
            }
          },
          "BcOQSFmMnl5BLA0a3RsPJo/RAPYJ4zmw4EVhumAEYk0e": {
            "registrationId": 1701057898,
            "currentRatchet": {
              "ephemeralKeyPair": {
                "pubKey": "BRGjhXUrnoGVYptDxk3ID+SLDrVABBF+0awY79MH4HoZ",
                "privKey": "SHHMOjgUaXUtd9ICvuxmyEY0h8yq6n6lOkpyJCq8omw="
              },
              "lastRemoteEphemeralKey": "BU0qPzuyeKyZ8PDJaU37RA5nCzftyPKBX4TPfBQRtEg0",
              "previousCounter": 3,
              "rootKey": "1YCCgr81FN2t72IxgY7VER/dpZzJPpqzpuvGZAdmINk="
            },
            "indexInfo": {
              "baseKey": "BcOQSFmMnl5BLA0a3RsPJo/RAPYJ4zmw4EVhumAEYk0e",
              "baseKeyType": 1,
              "closed": 1676589126754,
              "used": 1676503152321,
              "created": 1676458652959,
              "remoteIdentityKey": "BZ3hAt1Kskouw5Zp//nyNDVOPjWQ9xgCBZVkKzpVoI9k"
            },
            "_chains": {
              "BTwZJSLzaiv5STBwMV4d0anQnxip6PGRomjVbzLMBUFh": {
                "chainKey": {
                  "counter": 0
                },
                "chainType": 2,
                "messageKeys": {}
              },
              "BU0qPzuyeKyZ8PDJaU37RA5nCzftyPKBX4TPfBQRtEg0": {
                "chainKey": {
                  "counter": 0,
                  "key": "sXg0fgWdlHNUrjEfoOvQUC8zCVn1AJJUu3Hrn27xcXs="
                },
                "chainType": 2,
                "messageKeys": {}
              },
              "BRGjhXUrnoGVYptDxk3ID+SLDrVABBF+0awY79MH4HoZ": {
                "chainKey": {
                  "counter": 8,
                  "key": "jMYzKiUyUQ1Tjz2y8Iu+XfVGUgbAdsPwLvZrdpOzReQ="
                },
                "chainType": 1,
                "messageKeys": {}
              }
            }
          },
          "Bb6JhaB417A2Wgd/EBJoTM6UQm8RiQNlNe3fhFj6o99V": {
            "registrationId": 319777117,
            "currentRatchet": {
              "ephemeralKeyPair": {
                "pubKey": "BYVR41eCkpKq0ez7zd7ssWF8yBFAqFonsEpL4UbXKp0S",
                "privKey": "gEDgHZ3K8jcl/D2rhWqNkgVr+Ozt0D1qwctDITdLm14="
              },
              "lastRemoteEphemeralKey": "BS/GuHW4+IXkjtO/ZEYr7YxSeLCE0dPe+Ik6X5xaO01S",
              "previousCounter": 1,
              "rootKey": "jN/g9nfHeDW2L6lrRBgsLtk7FVEzxwhow+De3bYjQb8="
            },
            "indexInfo": {
              "baseKey": "Bb6JhaB417A2Wgd/EBJoTM6UQm8RiQNlNe3fhFj6o99V",
              "baseKeyType": 2,
              "closed": 1676590383238,
              "used": 1676589137920,
              "created": 1676589126766,
              "remoteIdentityKey": "BZPnkN86lxSoJi/g2V1AXqzT8xi9xjvGBjS45kAhjEEP"
            },
            "_chains": {
              "Ba6Z5LgGFAdNMVxZke1rqJhyvlzaXsuWaEJoZn8n3Utu": {
                "chainKey": {
                  "counter": 0
                },
                "chainType": 2,
                "messageKeys": {}
              },
              "BS/GuHW4+IXkjtO/ZEYr7YxSeLCE0dPe+Ik6X5xaO01S": {
                "chainKey": {
                  "counter": 0,
                  "key": "r2CMfIGfwX6Nj5eN0jDJf3cN9JuV46YoZfJBZJ+5ofs="
                },
                "chainType": 2,
                "messageKeys": {}
              },
              "BYVR41eCkpKq0ez7zd7ssWF8yBFAqFonsEpL4UbXKp0S": {
                "chainKey": {
                  "counter": 0,
                  "key": "Ftbn12Krzu8S9IPmIu1FsLUJaZAKZH6AKHLsE8NtFyQ="
                },
                "chainType": 1,
                "messageKeys": {}
              }
            }
          },
          "BXfQWoPKbs2kLDqwH3RuQogUX9lbpLius30hSOaPK6x8": {
            "registrationId": 319777117,
            "currentRatchet": {
              "ephemeralKeyPair": {
                "pubKey": "BT+4xS5d9hJTkm9OK9jR1N70BaH8O7qO3Mm3a91RvPRY",
                "privKey": "eP6K0wJmraMH0X5szZvCl331rsWYgbQ06VU7Yydy2mc="
              },
              "lastRemoteEphemeralKey": "BXyzsT/qNDg98OBkxIQApuxRSom8wT5ubWepyPkHBTUk",
              "previousCounter": 0,
              "rootKey": "8OUdGQK9np9ryXmdCPnzFXfc0bi6+QsfnnrFffBcD+0="
            },
            "indexInfo": {
              "baseKey": "BXfQWoPKbs2kLDqwH3RuQogUX9lbpLius30hSOaPK6x8",
              "baseKeyType": 1,
              "closed": -1,
              "used": 1676590383235,
              "created": 1676590383235,
              "remoteIdentityKey": "BZPnkN86lxSoJi/g2V1AXqzT8xi9xjvGBjS45kAhjEEP"
            },
            "_chains": {
              "BT+4xS5d9hJTkm9OK9jR1N70BaH8O7qO3Mm3a91RvPRY": {
                "chainKey": {
                  "counter": 0,
                  "key": "Gj4cRtonSlB2XvePD6uou9i2KvzC5fX2QmOCfb0RID8="
                },
                "chainType": 1,
                "messageKeys": {}
              }
            },
            "pendingPreKey": {
              "signedKeyId": 0,
              "baseKey": "BXfQWoPKbs2kLDqwH3RuQogUX9lbpLius30hSOaPK6x8",
              "preKeyId": 12393011
            }
          }
        },
        "version": "v1"
      },
      "6287784028546.0": {
        "_sessions": {
          "BUquL4+z+OMf+cyTwAxA/tBcuY2d2GRZBPHlhrqmza9s": {
            "registrationId": 1900696119,
            "currentRatchet": {
              "ephemeralKeyPair": {
                "pubKey": "BRT6VC/kT5UWF8CLY83s3Evsr/VqjbGCs04u1PF+pVJH",
                "privKey": "eE0OdEs72mTpT+slHBS4DjMSOlLm0bPdeApQLO5WS0w="
              },
              "lastRemoteEphemeralKey": "BXIwPhDZKa9KN9iWYhCgf1+HzO7404R8kychuH+tC2wA",
              "previousCounter": 0,
              "rootKey": "/ymvHTXRjNnvg47/CBNrZ8s27/tfQsQIPk8f/3iYNbg="
            },
            "indexInfo": {
              "baseKey": "BUquL4+z+OMf+cyTwAxA/tBcuY2d2GRZBPHlhrqmza9s",
              "baseKeyType": 1,
              "closed": -1,
              "used": 1676418253886,
              "created": 1676418253886,
              "remoteIdentityKey": "BWY8e2bC06vwygVSOZBtAH0o+G5D2V8+8uHhSlPW4T0F"
            },
            "_chains": {
              "BRT6VC/kT5UWF8CLY83s3Evsr/VqjbGCs04u1PF+pVJH": {
                "chainKey": {
                  "counter": 7,
                  "key": "nhprZHt8ve5AhK/1Ymx7Bb6GsPcKRarf1pxUa0ETL0s="
                },
                "chainType": 1,
                "messageKeys": {}
              }
            },
            "pendingPreKey": {
              "signedKeyId": 1,
              "baseKey": "BUquL4+z+OMf+cyTwAxA/tBcuY2d2GRZBPHlhrqmza9s",
              "preKeyId": 4690009
            }
          }
        },
        "version": "v1"
      },
      "6283169306546.0": {
        "_sessions": {
          "BfcKgrD6VCepyvalMVqjD1QZGYnh7fft4vXCLwSS9Iwq": {
            "registrationId": 984733846,
            "currentRatchet": {
              "ephemeralKeyPair": {
                "pubKey": "BegYxX7JzpKC8P3fkOOSHDpx+w2klH/5z0CIY5RdBatV",
                "privKey": "cPQisoXxcf3Qjtyt7jyLIvg/NFuVnLRd4GJ/7RzDB28="
              },
              "lastRemoteEphemeralKey": "BcAqu9I3C/cZ8jCgh4MQMgRfwj9wlGKrmY7Sw5ULCC95",
              "previousCounter": 0,
              "rootKey": "PM1H7ifrK1kEWte3bNN4epbzO3SWFQliGoNCHUGpmFk="
            },
            "indexInfo": {
              "baseKey": "BfcKgrD6VCepyvalMVqjD1QZGYnh7fft4vXCLwSS9Iwq",
              "baseKeyType": 2,
              "closed": -1,
              "used": 1676469967243,
              "created": 1676469967243,
              "remoteIdentityKey": "BfmHbwptwg8h+2fGZXoe3RXEgCIwIF1iP9HP3C4hOKpo"
            },
            "_chains": {
              "BcAqu9I3C/cZ8jCgh4MQMgRfwj9wlGKrmY7Sw5ULCC95": {
                "chainKey": {
                  "counter": 4,
                  "key": "UQtLdEoKyXV9TstneT816gNxkWNNsfbe99kNNASYYEU="
                },
                "chainType": 2,
                "messageKeys": {
                  "0": "NzkmGC+ferM7k06aBc2WhhGfk7RW9mEfAVmh9OVlyCQ=",
                  "2": "/kfzeings7OxgYA5ef/4CBYMetMk9iesSb6QLWoCfpo="
                }
              },
              "BegYxX7JzpKC8P3fkOOSHDpx+w2klH/5z0CIY5RdBatV": {
                "chainKey": {
                  "counter": -1,
                  "key": "ZVTFXIug5GAPhMVgZPX4TfQ9gPNROgi7KYYLmQUunis="
                },
                "chainType": 1,
                "messageKeys": {}
              }
            }
          }
        },
        "version": "v1"
      }
    },
    "appStateSyncKeys": {
      "AAAAAPtW": {
        "keyData": "jKDyHxuF2BLJBY4okqVMIRVm2Rc8caV+8c1tHZ5Rdog=",
        "fingerprint": {
          "rawId": 1854469333,
          "currentIndex": 1,
          "deviceIndexes": [
            0,
            1
          ]
        },
        "timestamp": "1676378379468"
      },
      "AAAAAPtX": {
        "keyData": "3nYVYl4SJ6h0xNrBcrUf6X/cc6gPoam3KGXovyiF4eM=",
        "fingerprint": {
          "rawId": 1854469333,
          "currentIndex": 1,
          "deviceIndexes": [
            0
          ]
        },
        "timestamp": "1676378515498"
      },
      "AAAAAPtV": {
        "keyData": "ALwZEgHxwxVo7YrBma5gTE5+uLQllL8l3tFWj1icCjs=",
        "fingerprint": {
          "rawId": 1854469333,
          "currentIndex": 1,
          "deviceIndexes": [
            0,
            1
          ]
        },
        "timestamp": "0"
      }
    },
    "appStateVersions": {
      "critical_unblock_low": null,
      "regular_high": null
    },
    "senderKeys": {
      "120363030444365532@g.us::6281392128956::0": [
        {
          "senderKeyId": 1769071447,
          "senderChainKey": {
            "iteration": 39,
            "seed": "Htx7pwIScynSoyWD4if+vP2EyPl7wm5vtucg6f6fIKY="
          },
          "senderSigningKey": {
            "public": "Bbmp9QYNCMBIRKAIH9nNcIbMM4f4nitRP5+4jaDLIOt4"
          },
          "senderMessageKeys": [
            {},
            {}
          ]
        }
      ],
      "120363030444365532@g.us::6281349838609:3::0": [
        {
          "senderKeyId": 215762992,
          "senderChainKey": {
            "iteration": 50,
            "seed": "3mVUDznac2RP+xeJxyCqfdSVnlw7eQIgg1ZWlixUlQQ="
          },
          "senderSigningKey": {
            "public": "BV0FfZ26tFnvWvtkFhXQ6qq/rjQiuBqgfNmeBqvvNPII",
            "private": "MNFqzkzBxLe6SloSvq/as8gfnBosyYiCMyYhvHOP/3Q="
          },
          "senderMessageKeys": []
        }
      ],
      "120363030444365532@g.us::6287784028546:3::0": [
        {
          "senderKeyId": 160241655,
          "senderChainKey": {
            "iteration": 137,
            "seed": "gHTTDZQ1ABylWuLwyZy2sL+qi95QigwSaTokqyCu2fU="
          },
          "senderSigningKey": {
            "public": "Bc6g9qiwgggEj952dWBKXML6xzN9OTKbSfpsRRVI5Xpe"
          },
          "senderMessageKeys": [
            {
              "iteration": 102,
              "seed": "n70WSAJjshf/f0gbdCA4nZrMMiM4mb1Z4/LvRiteSlg="
            },
            {},
            {}
          ]
        },
        {
          "senderKeyId": 160241655,
          "senderChainKey": {
            "iteration": 104,
            "seed": "6bAqDXYC+9//AcehsPcOmtnfTEHdWjVs9Yyhmb/NLaw="
          },
          "senderSigningKey": {
            "public": "Bc6g9qiwgggEj952dWBKXML6xzN9OTKbSfpsRRVI5Xpe"
          },
          "senderMessageKeys": []
        },
        {
          "senderKeyId": 160241655,
          "senderChainKey": {
            "iteration": 107,
            "seed": "CK2Yt37pGNfVVvixB6T5K2japhbfnLeM3JfkJvxN+Ss="
          },
          "senderSigningKey": {
            "public": "Bc6g9qiwgggEj952dWBKXML6xzN9OTKbSfpsRRVI5Xpe"
          },
          "senderMessageKeys": []
        },
        {
          "senderKeyId": 160241655,
          "senderChainKey": {
            "iteration": 125,
            "seed": "TJI4NEnB1L6iwiIF+ktS431r6ZjVdY6cJ+IT6f9i9JQ="
          },
          "senderSigningKey": {
            "public": "Bc6g9qiwgggEj952dWBKXML6xzN9OTKbSfpsRRVI5Xpe"
          },
          "senderMessageKeys": []
        },
        {
          "senderKeyId": 160241655,
          "senderChainKey": {
            "iteration": 128,
            "seed": "/HvFhZkZopTQ0IGPOmSRfXcHRF0aQFAc4aYoztevcJU="
          },
          "senderSigningKey": {
            "public": "Bc6g9qiwgggEj952dWBKXML6xzN9OTKbSfpsRRVI5Xpe"
          },
          "senderMessageKeys": []
        },
        {
          "senderKeyId": 160241655,
          "senderChainKey": {
            "iteration": 129,
            "seed": "9p/cy377SCM1lGUM7vEDCb8StPdxERd6LD6TeagQuPc="
          },
          "senderSigningKey": {
            "public": "Bc6g9qiwgggEj952dWBKXML6xzN9OTKbSfpsRRVI5Xpe"
          },
          "senderMessageKeys": []
        },
        {
          "senderKeyId": 160241655,
          "senderChainKey": {
            "iteration": 135,
            "seed": "dyi0rJ+wjNYdqi8JPYBNngavXatboim4byIrVrLCHRk="
          },
          "senderSigningKey": {
            "public": "Bc6g9qiwgggEj952dWBKXML6xzN9OTKbSfpsRRVI5Xpe"
          }
        }
      ],
      "120363030444365532@g.us::6281327238906:24::0": [
        {
          "senderKeyId": 1155025601,
          "senderChainKey": {
            "iteration": 149,
            "seed": "VO2UqxPSJRyhn+8nH4WF/EUqqQKbYV6WqN9pLu2wxBg="
          },
          "senderSigningKey": {
            "public": "BZGZ+b8yXB3kx5ZBnV1WGnfGhZP1u3S2kLcbrR3W6Vhn"
          },
          "senderMessageKeys": [
            {
              "iteration": 120,
              "seed": "Hhk/NcbTUG5vPyqelBlwC23dm7BzquQhScjEDE2PoPs="
            },
            {},
            {},
            {},
            {}
          ]
        },
        {
          "senderKeyId": 1155025601,
          "senderChainKey": {
            "iteration": 121,
            "seed": "vPRJU+8oOfFzNTPVZb/T4Kybn1psmC+BMSSuRwp4fyM="
          },
          "senderSigningKey": {
            "public": "BZGZ+b8yXB3kx5ZBnV1WGnfGhZP1u3S2kLcbrR3W6Vhn"
          },
          "senderMessageKeys": []
        },
        {
          "senderKeyId": 1155025601,
          "senderChainKey": {
            "iteration": 145,
            "seed": "aoW35mLVVJe56D0qW/TrmcjAPcb+uvnyRz6R5SRm31c="
          },
          "senderSigningKey": {
            "public": "BZGZ+b8yXB3kx5ZBnV1WGnfGhZP1u3S2kLcbrR3W6Vhn"
          },
          "senderMessageKeys": []
        },
        {
          "senderKeyId": 1771764737,
          "senderChainKey": {
            "iteration": 14,
            "seed": "OAedbpzg3dZty4tW7G7PdZeu9zkMRPpTqHlz2hTkcAY="
          },
          "senderSigningKey": {
            "public": "BcP+QUa93d6fP/s+YPBTAvzpHSMzSgBKPxuVWAotjORv"
          },
          "senderMessageKeys": []
        },
        {
          "senderKeyId": 1771764737,
          "senderChainKey": {
            "iteration": 10,
            "seed": "Hw15bbGkDwl5kVml0EZFtI0KmXVuiiKgIKNXiux0ahg="
          },
          "senderSigningKey": {
            "public": "BcP+QUa93d6fP/s+YPBTAvzpHSMzSgBKPxuVWAotjORv"
          }
        }
      ],
      "120363030444365532@g.us::6281333154367::0": [
        {
          "senderKeyId": 1275067554,
          "senderChainKey": {
            "iteration": 40,
            "seed": "rYM9n0URyS5IOJxvdVtLx2kpsfmSLFUkAmxAZ1DXriE="
          },
          "senderSigningKey": {
            "public": "BQnadXgD6XfeZZNl3swsB4zj/rtEHQhzlgsf/seh51kU"
          },
          "senderMessageKeys": [
            {}
          ]
        }
      ],
      "status@broadcast::6283169306546::0": [
        {
          "senderKeyId": 188318321,
          "senderChainKey": {
            "iteration": 0,
            "seed": "cRaXxoC6uWbpGjsKVOu83cgg3zOPJxfUcqpAjO9EneA="
          },
          "senderSigningKey": {
            "public": "BattXSBOXXBE5TVF+W1UgFz34hawTJ8omI0x644DfK5V"
          }
        }
      ]
    },
    "senderKeyMemory": {
      "120363030444365532@g.us": {
        "6281327238906@s.whatsapp.net": true,
        "6281327238906:24@s.whatsapp.net": true,
        "6281333154367@s.whatsapp.net": true,
        "6281349838609@s.whatsapp.net": true,
        "6281392128956@s.whatsapp.net": true,
        "6287784028546@s.whatsapp.net": true,
        "6287784028546:3@s.whatsapp.net": true
      }
    }
  }
}
